Metadata-Version: 1.1
Name: omicexperiment
Version: 0.1.2.dev1
Summary: For analysis of omic experiments.
Home-page: https://github.com/bassio/omicexperiment
Author: Ahmed Bassiouni
Author-email: ahmedbassi@gmail.com
License: BSD
Download-URL: https://github.com/bassio/omicexperiment/tarball/0.1.2-dev1
Keywords: bioinformatics
Platform: UNKNOWN
Classifier: Programming Language :: Python
Classifier: License :: OSI Approved :: BSD License
Classifier: Topic :: Scientific/Engineering :: Bio-Informatics
